{"title": "Synthesis of two classes of small RNA species in vivo and in vitro", "pubDate": "1977", "PMCID": "", "DOI": "10.1021/bi00639a029", "PMID": "911771", "abstract": "", "author": [{"author": "G Zieve", "affiliation": [], "href": "/?term=Zieve+G&cauthor_id=911771"}, {"author": "B J Benecke", "affiliation": [], "href": "/?term=Benecke+BJ&cauthor_id=911771"}, {"author": "S Penman", "affiliation": [], "href": "/?term=Penman+S&cauthor_id=911771"}], "refPMID": [], "citedInPMID": ["911771", "29995556", "27852926", "27558685", "24306891", "22740346", "20675720", "16959964", "14701755", "10634318", "9820822", "9653126", "7422543", "6896909", "6896456", "6325172", "6200485", "6182525", "6179077", "6164523", "6159360", "6084597", "3545184", "3459149", "2948154", "2837648", "2477683", "2450332", "2442600", "2411548", "2349089", "1702200", "1697065", "1646389", "424295"], "body": ""}